<?xml version="1.0" encoding="utf-8"?>
<!DOCTYPE hibernate-mapping PUBLIC "-//Hibernate/Hibernate Mapping DTD 3.0//EN"
"http://www.hibernate.org/dtd/hibernate-mapping-3.0.dtd">
<!-- 
    Mapping file autogenerated by MyEclipse Persistence Tools
-->
<hibernate-mapping>
    <class name="cn.sf_soft.office.approval.model.VehicleConversionDetail" table="vehicle_conversion_detail" schema="dbo">
        <id name="conversionDetailId" type="java.lang.String">
            <column name="conversion_detail_id" length="40" />
            <generator class="assigned" />
        </id>
        <property name="inDetailId" type="java.lang.String">
            <column name="in_detail_id" length="40" />
        </property>
        <property name="vehicleVin" type="java.lang.String">
            <column name="vehicle_vin" length="30" />
        </property>
        <property name="vehicleKind" type="java.lang.Short">
            <column name="vehicle_kind" />
        </property>
        <property name="conversionNo" type="java.lang.String">
            <column name="conversion_no" length="40" />
        </property>
        <property name="conversionType" type="java.lang.Short">
            <column name="conversion_type" />
        </property>
        <property name="status" type="java.lang.Short">
            <column name="status" />
        </property>
        <property name="itemId" type="java.lang.String">
            <column name="item_id" length="40" />
        </property>
        <property name="itemNo" type="java.lang.String">
            <column name="item_no" length="20" />
        </property>
        <property name="itemName" type="java.lang.String">
            <column name="item_name" />
        </property>
        <property name="supplierId" type="java.lang.String">
            <column name="supplier_id" length="40" />
        </property>
        <property name="supplierNo" type="java.lang.String">
            <column name="supplier_no" length="40" />
        </property>
        <property name="supplierName" type="java.lang.String">
            <column name="supplier_name" />
        </property>
        <property name="itemCost" type="java.math.BigDecimal">
            <column name="item_cost" precision="9" />
        </property>
          <property name="remark" type="java.lang.String">
            <column name="remark" />
        </property>
        <property name="paymentStatus" type="java.lang.Short">
            <column name="payment_status" />
        </property>
        <property name="varyFlag" type="java.lang.Boolean">
            <column name="vary_flag" />
        </property>
        <property name="confirmMan" type="java.lang.String">
            <column name="confirm_man" />
        </property>
        <property name="confirmTime" type="java.sql.Timestamp">
            <column name="confirm_time" length="23" />
        </property>
        <property name="itemCostOri" type="java.math.BigDecimal">
            <column name="item_cost_ori" precision="9" />
        </property>
        <property name="confirmPriceDate" type="java.sql.Timestamp">
            <column name="confirm_price_date" length="23" />
        </property>
        <property name="confirmerPrice" type="java.lang.String">
            <column name="confirmer_price" />
        </property>
        <property name="vehicleId" type="java.lang.String">
            <column name="vehicle_id" length="40" />
        </property>
        <property name="futurePayDate" type="java.sql.Timestamp">
            <column name="future_pay_date" length="23" />
        </property>
        <property name="saleContractItemId" type="java.lang.String">
            <column name="sale_contract_item_id" length="40" />
        </property>
        <property name="confirmUnitNo" type="java.lang.String">
            <column name="confirm_unit_no" length="40" />
        </property>
        <property name="confirmUnitName" type="java.lang.String">
            <column name="confirm_unit_name" />
        </property>
        <property name="confirmManNo" type="java.lang.String">
            <column name="confirm_man_no" length="10" />
        </property>
        <property name="taxMoney" type="java.math.BigDecimal">
            <column name="tax_money" />
        </property>
        <property name="noTaxMoney" type="java.math.BigDecimal">
            <column name="no_tax_money" />
        </property>
        <property name="tax" type="java.math.BigDecimal">
            <column name="tax" />
        </property>
        <property name="taxRate" type="java.math.BigDecimal">
            <column name="tax_rate" precision="9" scale="4" />
        </property>

        <property name="isAutoRelation" type="java.lang.Boolean">
            <column name="is_auto_relation" />
        </property>
        <property name="conversionTime" type="java.sql.Timestamp">
            <column name="conversion_time" length="23" />
        </property>
        <property name="conversionId" type="java.lang.String">
            <column name="conversion_id" />
        </property>
        <property name="groupId" type="java.lang.String">
            <column name="group_id" />
        </property>
        <property name="vocdId" type="java.lang.String">
            <column name="vocd_id" />
        </property>
    </class>
</hibernate-mapping>
